iftracer/sdk/__init__.py
iftracer/sdk/config/__init__.py
iftracer/sdk/decorators/__init__.py
iftracer/sdk/decorators/base.py
iftracer/sdk/fetcher.py
iftracer/sdk/instruments.py
iftracer/sdk/metrics/__init__.py
iftracer/sdk/metrics/metrics.py
iftracer/sdk/prompts/__init__.py
iftracer/sdk/prompts/client.py
iftracer/sdk/prompts/model.py
iftracer/sdk/prompts/registry.py
iftracer/sdk/telemetry.py
iftracer/sdk/traceutils/__init__.py
iftracer/sdk/traceutils/consts.py
iftracer/sdk/traceutils/set_trace_utils.py
iftracer/sdk/traceutils/tests/__init__.py
iftracer/sdk/traceutils/tests/test_openai2_vanilla.py
iftracer/sdk/traceutils/trace_model_utils.py
iftracer/sdk/tracing/__init__.py
iftracer/sdk/tracing/content_allow_list.py
iftracer/sdk/tracing/context_manager.py
iftracer/sdk/tracing/manual.py
iftracer/sdk/tracing/tracing.py
iftracer/sdk/utils/__init__.py
iftracer/sdk/utils/in_memory_span_exporter.py
iftracer/sdk/utils/json_encoder.py
iftracer/sdk/utils/package_check.py
iftracer/sdk/version.py
iftracer_sdk-0.2.1.dist-info/METADATA
iftracer_sdk-0.2.1.dist-info/WHEEL
iftracer_sdk-0.2.1.dist-info/RECORD
