Metadata-Version: 2.3
Name: iftracer-sdk
Version: 0.2.1
Summary: Iftracer Software Development Kit (SDK) for Python
License: Apache-2.0
Author: Gal Kleinman
Author-email: gal@traceloop.com
Requires-Python: >=3.9,<4
Classifier: License :: OSI Approved :: Apache Software License
Classifier: Programming Language :: Python :: 3
Classifier: Programming Language :: Python :: 3.9
Classifier: Programming Language :: Python :: 3.10
Classifier: Programming Language :: Python :: 3.11
Classifier: Programming Language :: Python :: 3.12
Classifier: Programming Language :: Python :: 3.13
Requires-Dist: aiohttp (==3.11.7)
Requires-Dist: colorama (>=0.4.6,<0.5.0)
Requires-Dist: deprecated (>=1.2.14,<2.0.0)
Requires-Dist: jinja2 (>=3.1.2,<4.0.0)
Requires-Dist: opentelemetry-api (>=1.25.0,<2.0.0)
Requires-Dist: opentelemetry-exporter-otlp-proto-grpc (>=1.25.0,<2.0.0)
Requires-Dist: opentelemetry-exporter-otlp-proto-http (>=1.25.0,<2.0.0)
Requires-Dist: opentelemetry-if-instrumentation-alephalpha (>=0.25.6,<0.26.0)
Requires-Dist: opentelemetry-if-instrumentation-anthropic (>=0.25.6,<0.26.0)
Requires-Dist: opentelemetry-if-instrumentation-bedrock (>=0.25.6,<0.26.0)
Requires-Dist: opentelemetry-if-instrumentation-chromadb (>=0.25.6,<0.26.0)
Requires-Dist: opentelemetry-if-instrumentation-cohere (>=0.25.6,<0.26.0)
Requires-Dist: opentelemetry-if-instrumentation-google-generativeai (>=0.25.6,<0.26.0)
Requires-Dist: opentelemetry-if-instrumentation-haystack (>=0.25.6,<0.26.0)
Requires-Dist: opentelemetry-if-instrumentation-langchain (>=0.25.6,<0.26.0)
Requires-Dist: opentelemetry-if-instrumentation-llamaindex (>=0.25.6,<0.26.0)
Requires-Dist: opentelemetry-if-instrumentation-marqo (>=0.25.6,<0.26.0)
Requires-Dist: opentelemetry-if-instrumentation-milvus (>=0.25.6,<0.26.0)
Requires-Dist: opentelemetry-if-instrumentation-mistralai (>=1.0.0,<2.0.0)
Requires-Dist: opentelemetry-if-instrumentation-ollama (>=0.25.6,<0.26.0)
Requires-Dist: opentelemetry-if-instrumentation-openai (>=0.25.6,<0.26.0)
Requires-Dist: opentelemetry-if-instrumentation-pinecone (>=0.25.6,<0.26.0)
Requires-Dist: opentelemetry-if-instrumentation-qdrant (>=0.25.6,<0.26.0)
Requires-Dist: opentelemetry-if-instrumentation-replicate (>=0.25.6,<0.26.0)
Requires-Dist: opentelemetry-if-instrumentation-together (>=0.25.6,<0.26.0)
Requires-Dist: opentelemetry-if-instrumentation-transformers (>=0.25.6,<0.26.0)
Requires-Dist: opentelemetry-if-instrumentation-vertexai (>=0.25.6,<0.26.0)
Requires-Dist: opentelemetry-if-instrumentation-watsonx (>=0.25.6,<0.26.0)
Requires-Dist: opentelemetry-if-instrumentation-weaviate (>=0.25.6,<0.26.0)
Requires-Dist: opentelemetry-if-semantic-conventions-ai (>=0.3.6,<0.4.0)
Requires-Dist: opentelemetry-instrumentation-requests (>=0.46b0,<0.47)
Requires-Dist: opentelemetry-instrumentation-sqlalchemy (>=0.46b0,<0.47)
Requires-Dist: opentelemetry-instrumentation-urllib3 (>=0.46b0,<0.47)
Requires-Dist: opentelemetry-sdk (>=1.25.0,<2.0.0)
Requires-Dist: posthog (>3.0.2,<4)
Requires-Dist: pydantic (>=1)
Requires-Dist: tenacity (>=8.2.3,<9.0.0)
Project-URL: Documentation, https://traceloop.com/docs/openllmetry
Project-URL: Repository, https://github.com/traceloop/openllmetry
